censys_bigquery/__init__.py
censys_bigquery/bigquery.py
censys_bigquery/cli.py
censys_bigquery_cli-1.1.1.dist-info/LICENSE
censys_bigquery_cli-1.1.1.dist-info/METADATA
censys_bigquery_cli-1.1.1.dist-info/WHEEL
censys_bigquery_cli-1.1.1.dist-info/entry_points.txt
censys_bigquery_cli-1.1.1.dist-info/top_level.txt
censys_bigquery_cli-1.1.1.dist-info/RECORD
