Metadata-Version: 2.1
Name: censys-bigquery-cli
Version: 1.1.1
Summary: A command line tool for Censys Enterprise Customers that allows BQ access via the command line.
Home-page: UNKNOWN
Author: Censys Team
Author-email: support@censys.io
License: Apache License, Version 2.0
Project-URL: Censys Homepage, https://censys.io/
Project-URL: Changelog, https://github.com/censys/censys-bigquery/releases
Project-URL: Tracker, https://github.com/censys/censys-bigquery/issues
Project-URL: Source, https://github.com/censys/censys-bigquery
Keywords: censys,bigquery,cli
Platform: UNKNOWN
Classifier: Topic :: Internet
Classifier: Topic :: Security
Classifier: Environment :: Console
Classifier: Natural Language :: English
Classifier: Intended Audience :: Developers
Classifier: Operating System :: OS Independent
Classifier: Development Status :: 4 - Beta
Classifier: License :: OSI Approved :: Apache Software License
Classifier: Programming Language :: Python
Classifier: Programming Language :: Python :: 3
Classifier: Programming Language :: Python :: 3.6
Classifier: Programming Language :: Python :: 3.7
Classifier: Programming Language :: Python :: 3.8
Classifier: Programming Language :: Python :: 3.9
Classifier: Programming Language :: Python :: Implementation :: PyPy
Requires-Python: >=3.6.0
Requires-Dist: google-cloud-bigquery (==1.18.0)
Requires-Dist: google-cloud-core (==1.0.3)
Provides-Extra: dev
Requires-Dist: flake8 (==3.9.2) ; extra == 'dev'
Requires-Dist: flake8-docstrings (==1.6.0) ; extra == 'dev'
Requires-Dist: flake8-pytest-style (==1.4.1) ; extra == 'dev'
Requires-Dist: flake8-simplify (==0.14.1) ; extra == 'dev'
Requires-Dist: flake8-comprehensions (==3.5.0) ; extra == 'dev'
Requires-Dist: pep8-naming (==0.11.1) ; extra == 'dev'
Requires-Dist: flake8-black (==0.2.1) ; extra == 'dev'
Requires-Dist: black (==21.5b1) ; extra == 'dev'
Requires-Dist: pytest (==6.2.4) ; extra == 'dev'
Requires-Dist: pytest-cov (==2.12.0) ; extra == 'dev'
Requires-Dist: mypy (==0.812) ; extra == 'dev'
Requires-Dist: twine (==3.4.1) ; extra == 'dev'
